vidcov/__init__.py
vidcov/vidcov.py
vidcov-1.0.0.dist-info/LICENSE
vidcov-1.0.0.dist-info/METADATA
vidcov-1.0.0.dist-info/WHEEL
vidcov-1.0.0.dist-info/entry_points.txt
vidcov-1.0.0.dist-info/top_level.txt
vidcov-1.0.0.dist-info/RECORD
